setup.cfg
setup.py
pytest_winnotify/__init__.py
pytest_winnotify/pytest.ico
pytest_winnotify/winnotify.py
pytest_winnotify.egg-info/PKG-INFO
pytest_winnotify.egg-info/SOURCES.txt
pytest_winnotify.egg-info/dependency_links.txt
pytest_winnotify.egg-info/entry_points.txt
pytest_winnotify.egg-info/requires.txt
pytest_winnotify.egg-info/top_level.txt