Metadata-Version: 1.0
Name: pytest-winnotify
Version: 0.4.1
Summary: Windows tray notifications for py.test results.
Home-page: https://github.com/robertobernabe/pytest-winnotify
Author: Florian Schaeffeler
Author-email: florian.schaeffeler@gmail.com
License: UNKNOWN
Keywords: pytest,pytest-,windows,notifications,py.test
Platform: Microsoft Windows
